README.md
setup.cfg
setup.py
pysharepoint/__init__.py
pysharepoint/interface.py
pysharepoint.egg-info/PKG-INFO
pysharepoint.egg-info/SOURCES.txt
pysharepoint.egg-info/dependency_links.txt
pysharepoint.egg-info/requires.txt
pysharepoint.egg-info/top_level.txt