Metadata-Version: 1.2
Name: pysharepoint
Version: 0.1.4
Summary: This a Python package to interact with Microsoft Sharepoint
Home-page: https://github.com/dexterai-lab/PyShare
Author: Debabrata Roy Chowdhury
Author-email: debabrata.rc@dexterai.com
License: GNU General Public License v3 (GPLv3)
Download-URL: https://github.com/dexterai-lab/pysharepoint/archive/0.1.4.tar.gz
Keywords: SHAREPOINT,PYTHON,MICROSOFT SHAREPOINT
Platform: UNKNOWN
Classifier: Development Status :: 3 - Alpha
Classifier: Intended Audience :: Developers
Classifier: Topic :: Scientific/Engineering :: Artificial Intelligence
Classifier: License :: OSI Approved :: GNU General Public License v3 (GPLv3)
Requires-Python: >=3.6.0
